GPSPhoto/__init__.py
GPSPhoto/gpsphoto.py
gpsphoto-2.2.1.dist-info/METADATA
gpsphoto-2.2.1.dist-info/RECORD
gpsphoto-2.2.1.dist-info/WHEEL
gpsphoto-2.2.1.dist-info/top_level.txt
