Metadata-Version: 2.1
Name: gpsphoto
Version: 2.2.1
Summary: Returns, Modifies, or Removes GPS Data from Exif Data in jpeg and tiff photos. Requires ExifRead, piexif, and PIL.
Home-page: http://www.jessgwiii.wordpress.com
Author: Jess Williams
Author-email: stripes.denomino@gmail.com
License: UNKNOWN
Platform: UNKNOWN
Classifier: Programming Language :: Python :: 2
Classifier: Programming Language :: Python :: 3
Classifier: License :: OSI Approved :: GNU Lesser General Public License v3 or later (LGPLv3+)
Classifier: Operating System :: OS Independent
